setup.py
afapi/__init__.py
afapi/appfirst_api.py
afapi/exceptions.py
afapi.egg-info/PKG-INFO
afapi.egg-info/SOURCES.txt
afapi.egg-info/dependency_links.txt
afapi.egg-info/requires.txt
afapi.egg-info/top_level.txt