Metadata-Version: 1.0
Name: afapi
Version: 1.0.4
Summary: A Python wrapper for interacting with AppFirst's APIs (v5)
